{
  "node": {
    "00bf8d99ef580fad813c94919f4cb24adf0e3ed397": {
      "workers": {
        "app/admin/page": {
          "moduleId": "(rsc)/./node_modules/next/dist/build/webpack/loaders/next-flight-action-entry-loader.js?actions=%5B%5B%22%2FUsers%2Fjason%2FDeveloper%2Factive%2Ffairway-match%2Fapp%2Fadmin%2Factions.ts%22%2C%5B%7B%22id%22%3A%2200bf8d99ef580fad813c94919f4cb24adf0e3ed397%22%2C%22exportedName%22%3A%22generatePodMatchLinksAction%22%2C%22filename%22%3A%22app%2Fadmin%2Factions.ts%22%7D%2C%7B%22id%22%3A%22403916acdd6d69e76c6377bb3aff8141ec11ad7fc4%22%2C%22exportedName%22%3A%22createTeamAction%22%2C%22filename%22%3A%22app%2Fadmin%2Factions.ts%22%7D%2C%7B%22id%22%3A%22404a35d0f1dfebf74479dbc920f2c7d41aafc38580%22%2C%22exportedName%22%3A%22createMatchAction%22%2C%22filename%22%3A%22app%2Fadmin%2Factions.ts%22%7D%2C%7B%22id%22%3A%224066c3b1b9d8e8324fc29f52918db190009c80608a%22%2C%22exportedName%22%3A%22saveTournamentAction%22%2C%22filename%22%3A%22app%2Fadmin%2Factions.ts%22%7D%2C%7B%22id%22%3A%22407ea0abe5b88ae9809e2de4026ecc56520a7c3c8b%22%2C%22exportedName%22%3A%22updateTeamSeedAction%22%2C%22filename%22%3A%22app%2Fadmin%2Factions.ts%22%7D%2C%7B%22id%22%3A%224083f1c18d8fdbcc793135b8fbca7978bd44fc431a%22%2C%22exportedName%22%3A%22createPodAction%22%2C%22filename%22%3A%22app%2Fadmin%2Factions.ts%22%7D%2C%7B%22id%22%3A%2240afe2f41f1d8d1af2d7799c64f3de602ec574e554%22%2C%22exportedName%22%3A%22updatePlayerAction%22%2C%22filename%22%3A%22app%2Fadmin%2Factions.ts%22%7D%2C%7B%22id%22%3A%2240c9ab6507d3b71bc341ba59f416adb9346efe604d%22%2C%22exportedName%22%3A%22createPlayerAction%22%2C%22filename%22%3A%22app%2Fadmin%2Factions.ts%22%7D%2C%7B%22id%22%3A%2240cbe6e25b29ac9f9bfdae235139989ff3a26ab7c5%22%2C%22exportedName%22%3A%22bulkImportRosterAction%22%2C%22filename%22%3A%22app%2Fadmin%2Factions.ts%22%7D%2C%7B%22id%22%3A%2240ea4f30172e23d30e697598480d16c02cb8330515%22%2C%22exportedName%22%3A%22assignTeamToPodAction%22%2C%22filename%22%3A%22app%2Fadmin%2Factions.ts%22%7D%2C%7B%22id%22%3A%2240fc08d1ef8bc8b91d588870baf911b144845b425f%22%2C%22exportedName%22%3A%22saveBracketSettingsAction%22%2C%22filename%22%3A%22app%2Fadmin%2Factions.ts%22%7D%5D%5D%5D&__client_imported__=!",
          "async": false
        }
      },
      "layer": {
        "app/admin/page": "rsc"
      },
      "filename": "app/admin/actions.ts",
      "exportedName": "generatePodMatchLinksAction"
    },
    "403916acdd6d69e76c6377bb3aff8141ec11ad7fc4": {
      "workers": {
        "app/admin/page": {
          "moduleId": "(rsc)/./node_modules/next/dist/build/webpack/loaders/next-flight-action-entry-loader.js?actions=%5B%5B%22%2FUsers%2Fjason%2FDeveloper%2Factive%2Ffairway-match%2Fapp%2Fadmin%2Factions.ts%22%2C%5B%7B%22id%22%3A%2200bf8d99ef580fad813c94919f4cb24adf0e3ed397%22%2C%22exportedName%22%3A%22generatePodMatchLinksAction%22%2C%22filename%22%3A%22app%2Fadmin%2Factions.ts%22%7D%2C%7B%22id%22%3A%22403916acdd6d69e76c6377bb3aff8141ec11ad7fc4%22%2C%22exportedName%22%3A%22createTeamAction%22%2C%22filename%22%3A%22app%2Fadmin%2Factions.ts%22%7D%2C%7B%22id%22%3A%22404a35d0f1dfebf74479dbc920f2c7d41aafc38580%22%2C%22exportedName%22%3A%22createMatchAction%22%2C%22filename%22%3A%22app%2Fadmin%2Factions.ts%22%7D%2C%7B%22id%22%3A%224066c3b1b9d8e8324fc29f52918db190009c80608a%22%2C%22exportedName%22%3A%22saveTournamentAction%22%2C%22filename%22%3A%22app%2Fadmin%2Factions.ts%22%7D%2C%7B%22id%22%3A%22407ea0abe5b88ae9809e2de4026ecc56520a7c3c8b%22%2C%22exportedName%22%3A%22updateTeamSeedAction%22%2C%22filename%22%3A%22app%2Fadmin%2Factions.ts%22%7D%2C%7B%22id%22%3A%224083f1c18d8fdbcc793135b8fbca7978bd44fc431a%22%2C%22exportedName%22%3A%22createPodAction%22%2C%22filename%22%3A%22app%2Fadmin%2Factions.ts%22%7D%2C%7B%22id%22%3A%2240afe2f41f1d8d1af2d7799c64f3de602ec574e554%22%2C%22exportedName%22%3A%22updatePlayerAction%22%2C%22filename%22%3A%22app%2Fadmin%2Factions.ts%22%7D%2C%7B%22id%22%3A%2240c9ab6507d3b71bc341ba59f416adb9346efe604d%22%2C%22exportedName%22%3A%22createPlayerAction%22%2C%22filename%22%3A%22app%2Fadmin%2Factions.ts%22%7D%2C%7B%22id%22%3A%2240cbe6e25b29ac9f9bfdae235139989ff3a26ab7c5%22%2C%22exportedName%22%3A%22bulkImportRosterAction%22%2C%22filename%22%3A%22app%2Fadmin%2Factions.ts%22%7D%2C%7B%22id%22%3A%2240ea4f30172e23d30e697598480d16c02cb8330515%22%2C%22exportedName%22%3A%22assignTeamToPodAction%22%2C%22filename%22%3A%22app%2Fadmin%2Factions.ts%22%7D%2C%7B%22id%22%3A%2240fc08d1ef8bc8b91d588870baf911b144845b425f%22%2C%22exportedName%22%3A%22saveBracketSettingsAction%22%2C%22filename%22%3A%22app%2Fadmin%2Factions.ts%22%7D%5D%5D%5D&__client_imported__=!",
          "async": false
        }
      },
      "layer": {
        "app/admin/page": "rsc"
      },
      "filename": "app/admin/actions.ts",
      "exportedName": "createTeamAction"
    },
    "404a35d0f1dfebf74479dbc920f2c7d41aafc38580": {
      "workers": {
        "app/admin/page": {
          "moduleId": "(rsc)/./node_modules/next/dist/build/webpack/loaders/next-flight-action-entry-loader.js?actions=%5B%5B%22%2FUsers%2Fjason%2FDeveloper%2Factive%2Ffairway-match%2Fapp%2Fadmin%2Factions.ts%22%2C%5B%7B%22id%22%3A%2200bf8d99ef580fad813c94919f4cb24adf0e3ed397%22%2C%22exportedName%22%3A%22generatePodMatchLinksAction%22%2C%22filename%22%3A%22app%2Fadmin%2Factions.ts%22%7D%2C%7B%22id%22%3A%22403916acdd6d69e76c6377bb3aff8141ec11ad7fc4%22%2C%22exportedName%22%3A%22createTeamAction%22%2C%22filename%22%3A%22app%2Fadmin%2Factions.ts%22%7D%2C%7B%22id%22%3A%22404a35d0f1dfebf74479dbc920f2c7d41aafc38580%22%2C%22exportedName%22%3A%22createMatchAction%22%2C%22filename%22%3A%22app%2Fadmin%2Factions.ts%22%7D%2C%7B%22id%22%3A%224066c3b1b9d8e8324fc29f52918db190009c80608a%22%2C%22exportedName%22%3A%22saveTournamentAction%22%2C%22filename%22%3A%22app%2Fadmin%2Factions.ts%22%7D%2C%7B%22id%22%3A%22407ea0abe5b88ae9809e2de4026ecc56520a7c3c8b%22%2C%22exportedName%22%3A%22updateTeamSeedAction%22%2C%22filename%22%3A%22app%2Fadmin%2Factions.ts%22%7D%2C%7B%22id%22%3A%224083f1c18d8fdbcc793135b8fbca7978bd44fc431a%22%2C%22exportedName%22%3A%22createPodAction%22%2C%22filename%22%3A%22app%2Fadmin%2Factions.ts%22%7D%2C%7B%22id%22%3A%2240afe2f41f1d8d1af2d7799c64f3de602ec574e554%22%2C%22exportedName%22%3A%22updatePlayerAction%22%2C%22filename%22%3A%22app%2Fadmin%2Factions.ts%22%7D%2C%7B%22id%22%3A%2240c9ab6507d3b71bc341ba59f416adb9346efe604d%22%2C%22exportedName%22%3A%22createPlayerAction%22%2C%22filename%22%3A%22app%2Fadmin%2Factions.ts%22%7D%2C%7B%22id%22%3A%2240cbe6e25b29ac9f9bfdae235139989ff3a26ab7c5%22%2C%22exportedName%22%3A%22bulkImportRosterAction%22%2C%22filename%22%3A%22app%2Fadmin%2Factions.ts%22%7D%2C%7B%22id%22%3A%2240ea4f30172e23d30e697598480d16c02cb8330515%22%2C%22exportedName%22%3A%22assignTeamToPodAction%22%2C%22filename%22%3A%22app%2Fadmin%2Factions.ts%22%7D%2C%7B%22id%22%3A%2240fc08d1ef8bc8b91d588870baf911b144845b425f%22%2C%22exportedName%22%3A%22saveBracketSettingsAction%22%2C%22filename%22%3A%22app%2Fadmin%2Factions.ts%22%7D%5D%5D%5D&__client_imported__=!",
          "async": false
        }
      },
      "layer": {
        "app/admin/page": "rsc"
      },
      "filename": "app/admin/actions.ts",
      "exportedName": "createMatchAction"
    },
    "4066c3b1b9d8e8324fc29f52918db190009c80608a": {
      "workers": {
        "app/admin/page": {
          "moduleId": "(rsc)/./node_modules/next/dist/build/webpack/loaders/next-flight-action-entry-loader.js?actions=%5B%5B%22%2FUsers%2Fjason%2FDeveloper%2Factive%2Ffairway-match%2Fapp%2Fadmin%2Factions.ts%22%2C%5B%7B%22id%22%3A%2200bf8d99ef580fad813c94919f4cb24adf0e3ed397%22%2C%22exportedName%22%3A%22generatePodMatchLinksAction%22%2C%22filename%22%3A%22app%2Fadmin%2Factions.ts%22%7D%2C%7B%22id%22%3A%22403916acdd6d69e76c6377bb3aff8141ec11ad7fc4%22%2C%22exportedName%22%3A%22createTeamAction%22%2C%22filename%22%3A%22app%2Fadmin%2Factions.ts%22%7D%2C%7B%22id%22%3A%22404a35d0f1dfebf74479dbc920f2c7d41aafc38580%22%2C%22exportedName%22%3A%22createMatchAction%22%2C%22filename%22%3A%22app%2Fadmin%2Factions.ts%22%7D%2C%7B%22id%22%3A%224066c3b1b9d8e8324fc29f52918db190009c80608a%22%2C%22exportedName%22%3A%22saveTournamentAction%22%2C%22filename%22%3A%22app%2Fadmin%2Factions.ts%22%7D%2C%7B%22id%22%3A%22407ea0abe5b88ae9809e2de4026ecc56520a7c3c8b%22%2C%22exportedName%22%3A%22updateTeamSeedAction%22%2C%22filename%22%3A%22app%2Fadmin%2Factions.ts%22%7D%2C%7B%22id%22%3A%224083f1c18d8fdbcc793135b8fbca7978bd44fc431a%22%2C%22exportedName%22%3A%22createPodAction%22%2C%22filename%22%3A%22app%2Fadmin%2Factions.ts%22%7D%2C%7B%22id%22%3A%2240afe2f41f1d8d1af2d7799c64f3de602ec574e554%22%2C%22exportedName%22%3A%22updatePlayerAction%22%2C%22filename%22%3A%22app%2Fadmin%2Factions.ts%22%7D%2C%7B%22id%22%3A%2240c9ab6507d3b71bc341ba59f416adb9346efe604d%22%2C%22exportedName%22%3A%22createPlayerAction%22%2C%22filename%22%3A%22app%2Fadmin%2Factions.ts%22%7D%2C%7B%22id%22%3A%2240cbe6e25b29ac9f9bfdae235139989ff3a26ab7c5%22%2C%22exportedName%22%3A%22bulkImportRosterAction%22%2C%22filename%22%3A%22app%2Fadmin%2Factions.ts%22%7D%2C%7B%22id%22%3A%2240ea4f30172e23d30e697598480d16c02cb8330515%22%2C%22exportedName%22%3A%22assignTeamToPodAction%22%2C%22filename%22%3A%22app%2Fadmin%2Factions.ts%22%7D%2C%7B%22id%22%3A%2240fc08d1ef8bc8b91d588870baf911b144845b425f%22%2C%22exportedName%22%3A%22saveBracketSettingsAction%22%2C%22filename%22%3A%22app%2Fadmin%2Factions.ts%22%7D%5D%5D%5D&__client_imported__=!",
          "async": false
        }
      },
      "layer": {
        "app/admin/page": "rsc"
      },
      "filename": "app/admin/actions.ts",
      "exportedName": "saveTournamentAction"
    },
    "407ea0abe5b88ae9809e2de4026ecc56520a7c3c8b": {
      "workers": {
        "app/admin/page": {
          "moduleId": "(rsc)/./node_modules/next/dist/build/webpack/loaders/next-flight-action-entry-loader.js?actions=%5B%5B%22%2FUsers%2Fjason%2FDeveloper%2Factive%2Ffairway-match%2Fapp%2Fadmin%2Factions.ts%22%2C%5B%7B%22id%22%3A%2200bf8d99ef580fad813c94919f4cb24adf0e3ed397%22%2C%22exportedName%22%3A%22generatePodMatchLinksAction%22%2C%22filename%22%3A%22app%2Fadmin%2Factions.ts%22%7D%2C%7B%22id%22%3A%22403916acdd6d69e76c6377bb3aff8141ec11ad7fc4%22%2C%22exportedName%22%3A%22createTeamAction%22%2C%22filename%22%3A%22app%2Fadmin%2Factions.ts%22%7D%2C%7B%22id%22%3A%22404a35d0f1dfebf74479dbc920f2c7d41aafc38580%22%2C%22exportedName%22%3A%22createMatchAction%22%2C%22filename%22%3A%22app%2Fadmin%2Factions.ts%22%7D%2C%7B%22id%22%3A%224066c3b1b9d8e8324fc29f52918db190009c80608a%22%2C%22exportedName%22%3A%22saveTournamentAction%22%2C%22filename%22%3A%22app%2Fadmin%2Factions.ts%22%7D%2C%7B%22id%22%3A%22407ea0abe5b88ae9809e2de4026ecc56520a7c3c8b%22%2C%22exportedName%22%3A%22updateTeamSeedAction%22%2C%22filename%22%3A%22app%2Fadmin%2Factions.ts%22%7D%2C%7B%22id%22%3A%224083f1c18d8fdbcc793135b8fbca7978bd44fc431a%22%2C%22exportedName%22%3A%22createPodAction%22%2C%22filename%22%3A%22app%2Fadmin%2Factions.ts%22%7D%2C%7B%22id%22%3A%2240afe2f41f1d8d1af2d7799c64f3de602ec574e554%22%2C%22exportedName%22%3A%22updatePlayerAction%22%2C%22filename%22%3A%22app%2Fadmin%2Factions.ts%22%7D%2C%7B%22id%22%3A%2240c9ab6507d3b71bc341ba59f416adb9346efe604d%22%2C%22exportedName%22%3A%22createPlayerAction%22%2C%22filename%22%3A%22app%2Fadmin%2Factions.ts%22%7D%2C%7B%22id%22%3A%2240cbe6e25b29ac9f9bfdae235139989ff3a26ab7c5%22%2C%22exportedName%22%3A%22bulkImportRosterAction%22%2C%22filename%22%3A%22app%2Fadmin%2Factions.ts%22%7D%2C%7B%22id%22%3A%2240ea4f30172e23d30e697598480d16c02cb8330515%22%2C%22exportedName%22%3A%22assignTeamToPodAction%22%2C%22filename%22%3A%22app%2Fadmin%2Factions.ts%22%7D%2C%7B%22id%22%3A%2240fc08d1ef8bc8b91d588870baf911b144845b425f%22%2C%22exportedName%22%3A%22saveBracketSettingsAction%22%2C%22filename%22%3A%22app%2Fadmin%2Factions.ts%22%7D%5D%5D%5D&__client_imported__=!",
          "async": false
        }
      },
      "layer": {
        "app/admin/page": "rsc"
      },
      "filename": "app/admin/actions.ts",
      "exportedName": "updateTeamSeedAction"
    },
    "4083f1c18d8fdbcc793135b8fbca7978bd44fc431a": {
      "workers": {
        "app/admin/page": {
          "moduleId": "(rsc)/./node_modules/next/dist/build/webpack/loaders/next-flight-action-entry-loader.js?actions=%5B%5B%22%2FUsers%2Fjason%2FDeveloper%2Factive%2Ffairway-match%2Fapp%2Fadmin%2Factions.ts%22%2C%5B%7B%22id%22%3A%2200bf8d99ef580fad813c94919f4cb24adf0e3ed397%22%2C%22exportedName%22%3A%22generatePodMatchLinksAction%22%2C%22filename%22%3A%22app%2Fadmin%2Factions.ts%22%7D%2C%7B%22id%22%3A%22403916acdd6d69e76c6377bb3aff8141ec11ad7fc4%22%2C%22exportedName%22%3A%22createTeamAction%22%2C%22filename%22%3A%22app%2Fadmin%2Factions.ts%22%7D%2C%7B%22id%22%3A%22404a35d0f1dfebf74479dbc920f2c7d41aafc38580%22%2C%22exportedName%22%3A%22createMatchAction%22%2C%22filename%22%3A%22app%2Fadmin%2Factions.ts%22%7D%2C%7B%22id%22%3A%224066c3b1b9d8e8324fc29f52918db190009c80608a%22%2C%22exportedName%22%3A%22saveTournamentAction%22%2C%22filename%22%3A%22app%2Fadmin%2Factions.ts%22%7D%2C%7B%22id%22%3A%22407ea0abe5b88ae9809e2de4026ecc56520a7c3c8b%22%2C%22exportedName%22%3A%22updateTeamSeedAction%22%2C%22filename%22%3A%22app%2Fadmin%2Factions.ts%22%7D%2C%7B%22id%22%3A%224083f1c18d8fdbcc793135b8fbca7978bd44fc431a%22%2C%22exportedName%22%3A%22createPodAction%22%2C%22filename%22%3A%22app%2Fadmin%2Factions.ts%22%7D%2C%7B%22id%22%3A%2240afe2f41f1d8d1af2d7799c64f3de602ec574e554%22%2C%22exportedName%22%3A%22updatePlayerAction%22%2C%22filename%22%3A%22app%2Fadmin%2Factions.ts%22%7D%2C%7B%22id%22%3A%2240c9ab6507d3b71bc341ba59f416adb9346efe604d%22%2C%22exportedName%22%3A%22createPlayerAction%22%2C%22filename%22%3A%22app%2Fadmin%2Factions.ts%22%7D%2C%7B%22id%22%3A%2240cbe6e25b29ac9f9bfdae235139989ff3a26ab7c5%22%2C%22exportedName%22%3A%22bulkImportRosterAction%22%2C%22filename%22%3A%22app%2Fadmin%2Factions.ts%22%7D%2C%7B%22id%22%3A%2240ea4f30172e23d30e697598480d16c02cb8330515%22%2C%22exportedName%22%3A%22assignTeamToPodAction%22%2C%22filename%22%3A%22app%2Fadmin%2Factions.ts%22%7D%2C%7B%22id%22%3A%2240fc08d1ef8bc8b91d588870baf911b144845b425f%22%2C%22exportedName%22%3A%22saveBracketSettingsAction%22%2C%22filename%22%3A%22app%2Fadmin%2Factions.ts%22%7D%5D%5D%5D&__client_imported__=!",
          "async": false
        }
      },
      "layer": {
        "app/admin/page": "rsc"
      },
      "filename": "app/admin/actions.ts",
      "exportedName": "createPodAction"
    },
    "40afe2f41f1d8d1af2d7799c64f3de602ec574e554": {
      "workers": {
        "app/admin/page": {
          "moduleId": "(rsc)/./node_modules/next/dist/build/webpack/loaders/next-flight-action-entry-loader.js?actions=%5B%5B%22%2FUsers%2Fjason%2FDeveloper%2Factive%2Ffairway-match%2Fapp%2Fadmin%2Factions.ts%22%2C%5B%7B%22id%22%3A%2200bf8d99ef580fad813c94919f4cb24adf0e3ed397%22%2C%22exportedName%22%3A%22generatePodMatchLinksAction%22%2C%22filename%22%3A%22app%2Fadmin%2Factions.ts%22%7D%2C%7B%22id%22%3A%22403916acdd6d69e76c6377bb3aff8141ec11ad7fc4%22%2C%22exportedName%22%3A%22createTeamAction%22%2C%22filename%22%3A%22app%2Fadmin%2Factions.ts%22%7D%2C%7B%22id%22%3A%22404a35d0f1dfebf74479dbc920f2c7d41aafc38580%22%2C%22exportedName%22%3A%22createMatchAction%22%2C%22filename%22%3A%22app%2Fadmin%2Factions.ts%22%7D%2C%7B%22id%22%3A%224066c3b1b9d8e8324fc29f52918db190009c80608a%22%2C%22exportedName%22%3A%22saveTournamentAction%22%2C%22filename%22%3A%22app%2Fadmin%2Factions.ts%22%7D%2C%7B%22id%22%3A%22407ea0abe5b88ae9809e2de4026ecc56520a7c3c8b%22%2C%22exportedName%22%3A%22updateTeamSeedAction%22%2C%22filename%22%3A%22app%2Fadmin%2Factions.ts%22%7D%2C%7B%22id%22%3A%224083f1c18d8fdbcc793135b8fbca7978bd44fc431a%22%2C%22exportedName%22%3A%22createPodAction%22%2C%22filename%22%3A%22app%2Fadmin%2Factions.ts%22%7D%2C%7B%22id%22%3A%2240afe2f41f1d8d1af2d7799c64f3de602ec574e554%22%2C%22exportedName%22%3A%22updatePlayerAction%22%2C%22filename%22%3A%22app%2Fadmin%2Factions.ts%22%7D%2C%7B%22id%22%3A%2240c9ab6507d3b71bc341ba59f416adb9346efe604d%22%2C%22exportedName%22%3A%22createPlayerAction%22%2C%22filename%22%3A%22app%2Fadmin%2Factions.ts%22%7D%2C%7B%22id%22%3A%2240cbe6e25b29ac9f9bfdae235139989ff3a26ab7c5%22%2C%22exportedName%22%3A%22bulkImportRosterAction%22%2C%22filename%22%3A%22app%2Fadmin%2Factions.ts%22%7D%2C%7B%22id%22%3A%2240ea4f30172e23d30e697598480d16c02cb8330515%22%2C%22exportedName%22%3A%22assignTeamToPodAction%22%2C%22filename%22%3A%22app%2Fadmin%2Factions.ts%22%7D%2C%7B%22id%22%3A%2240fc08d1ef8bc8b91d588870baf911b144845b425f%22%2C%22exportedName%22%3A%22saveBracketSettingsAction%22%2C%22filename%22%3A%22app%2Fadmin%2Factions.ts%22%7D%5D%5D%5D&__client_imported__=!",
          "async": false
        }
      },
      "layer": {
        "app/admin/page": "rsc"
      },
      "filename": "app/admin/actions.ts",
      "exportedName": "updatePlayerAction"
    },
    "40c9ab6507d3b71bc341ba59f416adb9346efe604d": {
      "workers": {
        "app/admin/page": {
          "moduleId": "(rsc)/./node_modules/next/dist/build/webpack/loaders/next-flight-action-entry-loader.js?actions=%5B%5B%22%2FUsers%2Fjason%2FDeveloper%2Factive%2Ffairway-match%2Fapp%2Fadmin%2Factions.ts%22%2C%5B%7B%22id%22%3A%2200bf8d99ef580fad813c94919f4cb24adf0e3ed397%22%2C%22exportedName%22%3A%22generatePodMatchLinksAction%22%2C%22filename%22%3A%22app%2Fadmin%2Factions.ts%22%7D%2C%7B%22id%22%3A%22403916acdd6d69e76c6377bb3aff8141ec11ad7fc4%22%2C%22exportedName%22%3A%22createTeamAction%22%2C%22filename%22%3A%22app%2Fadmin%2Factions.ts%22%7D%2C%7B%22id%22%3A%22404a35d0f1dfebf74479dbc920f2c7d41aafc38580%22%2C%22exportedName%22%3A%22createMatchAction%22%2C%22filename%22%3A%22app%2Fadmin%2Factions.ts%22%7D%2C%7B%22id%22%3A%224066c3b1b9d8e8324fc29f52918db190009c80608a%22%2C%22exportedName%22%3A%22saveTournamentAction%22%2C%22filename%22%3A%22app%2Fadmin%2Factions.ts%22%7D%2C%7B%22id%22%3A%22407ea0abe5b88ae9809e2de4026ecc56520a7c3c8b%22%2C%22exportedName%22%3A%22updateTeamSeedAction%22%2C%22filename%22%3A%22app%2Fadmin%2Factions.ts%22%7D%2C%7B%22id%22%3A%224083f1c18d8fdbcc793135b8fbca7978bd44fc431a%22%2C%22exportedName%22%3A%22createPodAction%22%2C%22filename%22%3A%22app%2Fadmin%2Factions.ts%22%7D%2C%7B%22id%22%3A%2240afe2f41f1d8d1af2d7799c64f3de602ec574e554%22%2C%22exportedName%22%3A%22updatePlayerAction%22%2C%22filename%22%3A%22app%2Fadmin%2Factions.ts%22%7D%2C%7B%22id%22%3A%2240c9ab6507d3b71bc341ba59f416adb9346efe604d%22%2C%22exportedName%22%3A%22createPlayerAction%22%2C%22filename%22%3A%22app%2Fadmin%2Factions.ts%22%7D%2C%7B%22id%22%3A%2240cbe6e25b29ac9f9bfdae235139989ff3a26ab7c5%22%2C%22exportedName%22%3A%22bulkImportRosterAction%22%2C%22filename%22%3A%22app%2Fadmin%2Factions.ts%22%7D%2C%7B%22id%22%3A%2240ea4f30172e23d30e697598480d16c02cb8330515%22%2C%22exportedName%22%3A%22assignTeamToPodAction%22%2C%22filename%22%3A%22app%2Fadmin%2Factions.ts%22%7D%2C%7B%22id%22%3A%2240fc08d1ef8bc8b91d588870baf911b144845b425f%22%2C%22exportedName%22%3A%22saveBracketSettingsAction%22%2C%22filename%22%3A%22app%2Fadmin%2Factions.ts%22%7D%5D%5D%5D&__client_imported__=!",
          "async": false
        }
      },
      "layer": {
        "app/admin/page": "rsc"
      },
      "filename": "app/admin/actions.ts",
      "exportedName": "createPlayerAction"
    },
    "40cbe6e25b29ac9f9bfdae235139989ff3a26ab7c5": {
      "workers": {
        "app/admin/page": {
          "moduleId": "(rsc)/./node_modules/next/dist/build/webpack/loaders/next-flight-action-entry-loader.js?actions=%5B%5B%22%2FUsers%2Fjason%2FDeveloper%2Factive%2Ffairway-match%2Fapp%2Fadmin%2Factions.ts%22%2C%5B%7B%22id%22%3A%2200bf8d99ef580fad813c94919f4cb24adf0e3ed397%22%2C%22exportedName%22%3A%22generatePodMatchLinksAction%22%2C%22filename%22%3A%22app%2Fadmin%2Factions.ts%22%7D%2C%7B%22id%22%3A%22403916acdd6d69e76c6377bb3aff8141ec11ad7fc4%22%2C%22exportedName%22%3A%22createTeamAction%22%2C%22filename%22%3A%22app%2Fadmin%2Factions.ts%22%7D%2C%7B%22id%22%3A%22404a35d0f1dfebf74479dbc920f2c7d41aafc38580%22%2C%22exportedName%22%3A%22createMatchAction%22%2C%22filename%22%3A%22app%2Fadmin%2Factions.ts%22%7D%2C%7B%22id%22%3A%224066c3b1b9d8e8324fc29f52918db190009c80608a%22%2C%22exportedName%22%3A%22saveTournamentAction%22%2C%22filename%22%3A%22app%2Fadmin%2Factions.ts%22%7D%2C%7B%22id%22%3A%22407ea0abe5b88ae9809e2de4026ecc56520a7c3c8b%22%2C%22exportedName%22%3A%22updateTeamSeedAction%22%2C%22filename%22%3A%22app%2Fadmin%2Factions.ts%22%7D%2C%7B%22id%22%3A%224083f1c18d8fdbcc793135b8fbca7978bd44fc431a%22%2C%22exportedName%22%3A%22createPodAction%22%2C%22filename%22%3A%22app%2Fadmin%2Factions.ts%22%7D%2C%7B%22id%22%3A%2240afe2f41f1d8d1af2d7799c64f3de602ec574e554%22%2C%22exportedName%22%3A%22updatePlayerAction%22%2C%22filename%22%3A%22app%2Fadmin%2Factions.ts%22%7D%2C%7B%22id%22%3A%2240c9ab6507d3b71bc341ba59f416adb9346efe604d%22%2C%22exportedName%22%3A%22createPlayerAction%22%2C%22filename%22%3A%22app%2Fadmin%2Factions.ts%22%7D%2C%7B%22id%22%3A%2240cbe6e25b29ac9f9bfdae235139989ff3a26ab7c5%22%2C%22exportedName%22%3A%22bulkImportRosterAction%22%2C%22filename%22%3A%22app%2Fadmin%2Factions.ts%22%7D%2C%7B%22id%22%3A%2240ea4f30172e23d30e697598480d16c02cb8330515%22%2C%22exportedName%22%3A%22assignTeamToPodAction%22%2C%22filename%22%3A%22app%2Fadmin%2Factions.ts%22%7D%2C%7B%22id%22%3A%2240fc08d1ef8bc8b91d588870baf911b144845b425f%22%2C%22exportedName%22%3A%22saveBracketSettingsAction%22%2C%22filename%22%3A%22app%2Fadmin%2Factions.ts%22%7D%5D%5D%5D&__client_imported__=!",
          "async": false
        }
      },
      "layer": {
        "app/admin/page": "rsc"
      },
      "filename": "app/admin/actions.ts",
      "exportedName": "bulkImportRosterAction"
    },
    "40ea4f30172e23d30e697598480d16c02cb8330515": {
      "workers": {
        "app/admin/page": {
          "moduleId": "(rsc)/./node_modules/next/dist/build/webpack/loaders/next-flight-action-entry-loader.js?actions=%5B%5B%22%2FUsers%2Fjason%2FDeveloper%2Factive%2Ffairway-match%2Fapp%2Fadmin%2Factions.ts%22%2C%5B%7B%22id%22%3A%2200bf8d99ef580fad813c94919f4cb24adf0e3ed397%22%2C%22exportedName%22%3A%22generatePodMatchLinksAction%22%2C%22filename%22%3A%22app%2Fadmin%2Factions.ts%22%7D%2C%7B%22id%22%3A%22403916acdd6d69e76c6377bb3aff8141ec11ad7fc4%22%2C%22exportedName%22%3A%22createTeamAction%22%2C%22filename%22%3A%22app%2Fadmin%2Factions.ts%22%7D%2C%7B%22id%22%3A%22404a35d0f1dfebf74479dbc920f2c7d41aafc38580%22%2C%22exportedName%22%3A%22createMatchAction%22%2C%22filename%22%3A%22app%2Fadmin%2Factions.ts%22%7D%2C%7B%22id%22%3A%224066c3b1b9d8e8324fc29f52918db190009c80608a%22%2C%22exportedName%22%3A%22saveTournamentAction%22%2C%22filename%22%3A%22app%2Fadmin%2Factions.ts%22%7D%2C%7B%22id%22%3A%22407ea0abe5b88ae9809e2de4026ecc56520a7c3c8b%22%2C%22exportedName%22%3A%22updateTeamSeedAction%22%2C%22filename%22%3A%22app%2Fadmin%2Factions.ts%22%7D%2C%7B%22id%22%3A%224083f1c18d8fdbcc793135b8fbca7978bd44fc431a%22%2C%22exportedName%22%3A%22createPodAction%22%2C%22filename%22%3A%22app%2Fadmin%2Factions.ts%22%7D%2C%7B%22id%22%3A%2240afe2f41f1d8d1af2d7799c64f3de602ec574e554%22%2C%22exportedName%22%3A%22updatePlayerAction%22%2C%22filename%22%3A%22app%2Fadmin%2Factions.ts%22%7D%2C%7B%22id%22%3A%2240c9ab6507d3b71bc341ba59f416adb9346efe604d%22%2C%22exportedName%22%3A%22createPlayerAction%22%2C%22filename%22%3A%22app%2Fadmin%2Factions.ts%22%7D%2C%7B%22id%22%3A%2240cbe6e25b29ac9f9bfdae235139989ff3a26ab7c5%22%2C%22exportedName%22%3A%22bulkImportRosterAction%22%2C%22filename%22%3A%22app%2Fadmin%2Factions.ts%22%7D%2C%7B%22id%22%3A%2240ea4f30172e23d30e697598480d16c02cb8330515%22%2C%22exportedName%22%3A%22assignTeamToPodAction%22%2C%22filename%22%3A%22app%2Fadmin%2Factions.ts%22%7D%2C%7B%22id%22%3A%2240fc08d1ef8bc8b91d588870baf911b144845b425f%22%2C%22exportedName%22%3A%22saveBracketSettingsAction%22%2C%22filename%22%3A%22app%2Fadmin%2Factions.ts%22%7D%5D%5D%5D&__client_imported__=!",
          "async": false
        }
      },
      "layer": {
        "app/admin/page": "rsc"
      },
      "filename": "app/admin/actions.ts",
      "exportedName": "assignTeamToPodAction"
    },
    "40fc08d1ef8bc8b91d588870baf911b144845b425f": {
      "workers": {
        "app/admin/page": {
          "moduleId": "(rsc)/./node_modules/next/dist/build/webpack/loaders/next-flight-action-entry-loader.js?actions=%5B%5B%22%2FUsers%2Fjason%2FDeveloper%2Factive%2Ffairway-match%2Fapp%2Fadmin%2Factions.ts%22%2C%5B%7B%22id%22%3A%2200bf8d99ef580fad813c94919f4cb24adf0e3ed397%22%2C%22exportedName%22%3A%22generatePodMatchLinksAction%22%2C%22filename%22%3A%22app%2Fadmin%2Factions.ts%22%7D%2C%7B%22id%22%3A%22403916acdd6d69e76c6377bb3aff8141ec11ad7fc4%22%2C%22exportedName%22%3A%22createTeamAction%22%2C%22filename%22%3A%22app%2Fadmin%2Factions.ts%22%7D%2C%7B%22id%22%3A%22404a35d0f1dfebf74479dbc920f2c7d41aafc38580%22%2C%22exportedName%22%3A%22createMatchAction%22%2C%22filename%22%3A%22app%2Fadmin%2Factions.ts%22%7D%2C%7B%22id%22%3A%224066c3b1b9d8e8324fc29f52918db190009c80608a%22%2C%22exportedName%22%3A%22saveTournamentAction%22%2C%22filename%22%3A%22app%2Fadmin%2Factions.ts%22%7D%2C%7B%22id%22%3A%22407ea0abe5b88ae9809e2de4026ecc56520a7c3c8b%22%2C%22exportedName%22%3A%22updateTeamSeedAction%22%2C%22filename%22%3A%22app%2Fadmin%2Factions.ts%22%7D%2C%7B%22id%22%3A%224083f1c18d8fdbcc793135b8fbca7978bd44fc431a%22%2C%22exportedName%22%3A%22createPodAction%22%2C%22filename%22%3A%22app%2Fadmin%2Factions.ts%22%7D%2C%7B%22id%22%3A%2240afe2f41f1d8d1af2d7799c64f3de602ec574e554%22%2C%22exportedName%22%3A%22updatePlayerAction%22%2C%22filename%22%3A%22app%2Fadmin%2Factions.ts%22%7D%2C%7B%22id%22%3A%2240c9ab6507d3b71bc341ba59f416adb9346efe604d%22%2C%22exportedName%22%3A%22createPlayerAction%22%2C%22filename%22%3A%22app%2Fadmin%2Factions.ts%22%7D%2C%7B%22id%22%3A%2240cbe6e25b29ac9f9bfdae235139989ff3a26ab7c5%22%2C%22exportedName%22%3A%22bulkImportRosterAction%22%2C%22filename%22%3A%22app%2Fadmin%2Factions.ts%22%7D%2C%7B%22id%22%3A%2240ea4f30172e23d30e697598480d16c02cb8330515%22%2C%22exportedName%22%3A%22assignTeamToPodAction%22%2C%22filename%22%3A%22app%2Fadmin%2Factions.ts%22%7D%2C%7B%22id%22%3A%2240fc08d1ef8bc8b91d588870baf911b144845b425f%22%2C%22exportedName%22%3A%22saveBracketSettingsAction%22%2C%22filename%22%3A%22app%2Fadmin%2Factions.ts%22%7D%5D%5D%5D&__client_imported__=!",
          "async": false
        }
      },
      "layer": {
        "app/admin/page": "rsc"
      },
      "filename": "app/admin/actions.ts",
      "exportedName": "saveBracketSettingsAction"
    }
  },
  "edge": {},
  "encryptionKey": "C5C7Dulr0KM7mS7LfDfJN+WMucOSBMrcpXg5gQeC/lk="
}